[{"time": "06:25:00", "route": "A3916", "headsign": "BILBAO (Aut.)", "service_id": "OP44LIN", "trip_id": "trp_A3916_950_OP44LIN_23100"}, {"time": "06:25:00", "route": "A3916", "headsign": "BILBAO (Aut.)", "service_id": "OP44LNBNV", "trip_id": "trp_A3916_950_OP44LNBNV_23100"}, {"time": "06:25:00", "route": "A3916", "headsign": "BILBAO (Aut.)", "service_id": "OP44LSUPV", "trip_id": "trp_A3916_950_OP44LSUPV_23100"}, {"time": "06:25:00", "route": "A3916", "headsign": "BILBAO (Aut.)", "service_id": "OP44VIN", "trip_id": "trp_A3916_950_OP44VIN_23100"}, {"time": "07:25:00", "route": "A3916", "headsign": "BILBAO (Aut.)", "service_id": "OP44LIN", "trip_id": "trp_A3916_950_OP44LIN_26700"}, {"time": "07:25:00", "route": "A3916", "headsign": "BILBAO (Aut.)", "service_id": "OP44LNBNV", "trip_id": "trp_A3916_950_OP44LNBNV_26700"}, {"time": "07:25:00", "route": "A3916", "headsign": "BILBAO (Aut.)", "service_id": "OP44LSUPV", "trip_id": "trp_A3916_950_OP44LSUPV_26700"}, {"time": "07:25:00", "route": "A3916", "headsign": "BILBAO (Aut.)", "service_id": "OP44VIN", "trip_id": "trp_A3916_950_OP44VIN_26700"}, {"time": "15:25:00", "route": "A3916", "headsign": "BILBAO (Aut.)", "service_id": "OP44LIN", "trip_id": "trp_A3916_950_OP44LIN_55500"}, {"time": "15:25:00", "route": "A3916", "headsign": "BILBAO (Aut.)", "service_id": "OP44LNBNV", "trip_id": "trp_A3916_950_OP44LNBNV_55500"}, {"time": "15:25:00", "route": "A3916", "headsign": "BILBAO (Aut.)", "service_id": "OP44LSUPV", "trip_id": "trp_A3916_950_OP44LSUPV_55500"}, {"time": "15:25:00", "route": "A3916", "headsign": "BILBAO (Aut.)", "service_id": "OP44VIN", "trip_id": "trp_A3916_950_OP44VIN_55500"}, {"time": "16:05:00", "route": "A3916", "headsign": "MUTRIKU", "service_id": "OP44LIN", "trip_id": "trp_A3916_949_OP44LIN_51000"}, {"time": "16:05:00", "route": "A3916", "headsign": "MUTRIKU", "service_id": "OP44LNBNV", "trip_id": "trp_A3916_949_OP44LNBNV_51000"}, {"time": "16:05:00", "route": "A3916", "headsign": "MUTRIKU", "service_id": "OP44LSUPV", "trip_id": "trp_A3916_949_OP44LSUPV_51000"}, {"time": "16:05:00", "route": "A3916", "headsign": "MUTRIKU", "service_id": "OP44VIN", "trip_id": "trp_A3916_949_OP44VIN_51000"}, {"time": "20:05:00", "route": "A3916", "headsign": "MUTRIKU", "service_id": "OP44LIN", "trip_id": "trp_A3916_949_OP44LIN_65400"}, {"time": "20:05:00", "route": "A3916", "headsign": "MUTRIKU", "service_id": "OP44LSUPV", "trip_id": "trp_A3916_949_OP44LSUPV_65400"}, {"time": "20:05:00", "route": "A3916", "headsign": "MUTRIKU", "service_id": "OP44VIN", "trip_id": "trp_A3916_949_OP44VIN_65400"}, {"time": "20:10:00", "route": "A3916", "headsign": "MUTRIKU", "service_id": "OP44LNBNV", "trip_id": "trp_A3916_949_OP44LNBNV_65400"}, {"time": "21:50:00", "route": "A3916", "headsign": "MUTRIKU", "service_id": "OP44LSUPV", "trip_id": "trp_A3916_949_OP44LSUPV_72600"}, {"time": "21:55:00", "route": "A3916", "headsign": "MUTRIKU", "service_id": "OP44LIN", "trip_id": "trp_A3916_949_OP44LIN_72600"}, {"time": "21:55:00", "route": "A3916", "headsign": "MUTRIKU", "service_id": "OP44VIN", "trip_id": "trp_A3916_949_OP44VIN_72600"}]